[{"country_id":"US","country_name":"United States","country_slug":"us","state_name":"Montana","state_slug":"montana","city":"Billings","city_slug":"billings","location_count":"11","court_count":"43"},{"country_id":"US","country_name":"United States","country_slug":"us","state_name":"Montana","state_slug":"montana","city":"Missoula","city_slug":"missoula","location_count":"8","court_count":"36"},{"country_id":"US","country_name":"United States","country_slug":"us","state_name":"Montana","state_slug":"montana","city":"Bozeman","city_slug":"bozeman","location_count":"6","court_count":"22"},{"country_id":"US","country_name":"United States","country_slug":"us","state_name":"Montana","state_slug":"montana","city":"Bigfork","city_slug":"bigfork","location_count":"4","court_count":"25"},{"country_id":"US","country_name":"United States","country_slug":"us","state_name":"Montana","state_slug":"montana","city":"Butte","city_slug":"butte","location_count":"4","court_count":"13"},{"country_id":"US","country_name":"United States","country_slug":"us","state_name":"Montana","state_slug":"montana","city":"Great Falls","city_slug":"great-falls","location_count":"4","court_count":"14"},{"country_id":"US","country_name":"United States","country_slug":"us","state_name":"Montana","state_slug":"montana","city":"Helena","city_slug":"helena","location_count":"4","court_count":"14"},{"country_id":"US","country_name":"United States","country_slug":"us","state_name":"Montana","state_slug":"montana","city":"Eureka","city_slug":"eureka","location_count":"3","court_count":"6"},{"country_id":"US","country_name":"United States","country_slug":"us","state_name":"Montana","state_slug":"montana","city":"Polson","city_slug":"polson","location_count":"3","court_count":"7"},{"country_id":"US","country_name":"United States","country_slug":"us","state_name":"Montana","state_slug":"montana","city":"Dillon","city_slug":"dillon","location_count":"2","court_count":"5"},{"country_id":"US","country_name":"United States","country_slug":"us","state_name":"Montana","state_slug":"montana","city":"Hamilton","city_slug":"hamilton","location_count":"2","court_count":"9"},{"country_id":"US","country_name":"United States","country_slug":"us","state_name":"Montana","state_slug":"montana","city":"Kalispell","city_slug":"kalispell","location_count":"2","court_count":"6"},{"country_id":"US","country_name":"United States","country_slug":"us","state_name":"Montana","state_slug":"montana","city":"Red Lodge","city_slug":"red-lodge","location_count":"2","court_count":"4"},{"country_id":"US","country_name":"United States","country_slug":"us","state_name":"Montana","state_slug":"montana","city":"Whitefish","city_slug":"whitefish","location_count":"2","court_count":"6"},{"country_id":"US","country_name":"United States","country_slug":"us","state_name":"Montana","state_slug":"montana","city":"Anaconda","city_slug":"anaconda","location_count":"1","court_count":"1"},{"country_id":"US","country_name":"United States","country_slug":"us","state_name":"Montana","state_slug":"montana","city":"Big Sky","city_slug":"big-sky","location_count":"1","court_count":"6"},{"country_id":"US","country_name":"United States","country_slug":"us","state_name":"Montana","state_slug":"montana","city":"Choteau","city_slug":"choteau","location_count":"1","court_count":"4"},{"country_id":"US","country_name":"United States","country_slug":"us","state_name":"Montana","state_slug":"montana","city":"Columbia Falls","city_slug":"columbia-falls","location_count":"1","court_count":"4"},{"country_id":"US","country_name":"United States","country_slug":"us","state_name":"Montana","state_slug":"montana","city":"Condon","city_slug":"condon","location_count":"1","court_count":"1"},{"country_id":"US","country_name":"United States","country_slug":"us","state_name":"Montana","state_slug":"montana","city":"East Helena","city_slug":"east-helena","location_count":"1","court_count":"12"},{"country_id":"US","country_name":"United States","country_slug":"us","state_name":"Montana","state_slug":"montana","city":"Ennis","city_slug":"ennis","location_count":"1","court_count":"4"},{"country_id":"US","country_name":"United States","country_slug":"us","state_name":"Montana","state_slug":"montana","city":"Fortine","city_slug":"fortine","location_count":"1","court_count":"2"},{"country_id":"US","country_name":"United States","country_slug":"us","state_name":"Montana","state_slug":"montana","city":"Gallatin Gateway","city_slug":"gallatin-gateway","location_count":"1","court_count":"2"},{"country_id":"US","country_name":"United States","country_slug":"us","state_name":"Montana","state_slug":"montana","city":"Joplin","city_slug":"joplin","location_count":"1","court_count":"2"},{"country_id":"US","country_name":"United States","country_slug":"us","state_name":"Montana","state_slug":"montana","city":"Livingston","city_slug":"livingston","location_count":"1","court_count":"3"},{"country_id":"US","country_name":"United States","country_slug":"us","state_name":"Montana","state_slug":"montana","city":"Miles City","city_slug":"miles-city","location_count":"1","court_count":"2"},{"country_id":"US","country_name":"United States","country_slug":"us","state_name":"Montana","state_slug":"montana","city":"Seeley Lake","city_slug":"seeley-lake","location_count":"1","court_count":"6"},{"country_id":"US","country_name":"United States","country_slug":"us","state_name":"Montana","state_slug":"montana","city":"Sidney","city_slug":"sidney","location_count":"1","court_count":"1"},{"country_id":"US","country_name":"United States","country_slug":"us","state_name":"Montana","state_slug":"montana","city":"Stevensville","city_slug":"stevensville","location_count":"1","court_count":"3"},{"country_id":"US","country_name":"United States","country_slug":"us","state_name":"Montana","state_slug":"montana","city":"Townsend","city_slug":"townsend","location_count":"1","court_count":"3"},{"country_id":"US","country_name":"United States","country_slug":"us","state_name":"Montana","state_slug":"montana","city":"Trailcreek","city_slug":"trailcreek","location_count":"1","court_count":"4"}]